g2pg/__init__.py
g2pg/_init_.py
g2pg/g2pg.py
g2pg-1.3.0.dist-info/LICENSE
g2pg-1.3.0.dist-info/METADATA
g2pg-1.3.0.dist-info/WHEEL
g2pg-1.3.0.dist-info/top_level.txt
g2pg-1.3.0.dist-info/RECORD
