Metadata-Version: 2.1
Name: g2pg
Version: 1.3.0
Summary: Google Sheets to Postgres DB using gspread and env files.
Home-page: https://github.com/jesska-f/g2pg
Author: Jessica Franks
Author-email: hello@jesska.co.za
License: MIT
Keywords: pandas,postgres,gspread,gsheets
Platform: UNKNOWN
Classifier: Programming Language :: Python :: 3
Classifier: Programming Language :: Python :: 3.6
Classifier: Programming Language :: Python :: 3.7
Classifier: Programming Language :: Python :: 3.8
Classifier: License :: OSI Approved :: MIT License
Classifier: Operating System :: OS Independent
Requires-Dist: gspread (==3.6.0)
Requires-Dist: gspread-dataframe (==3.0.7)
Requires-Dist: oauth2client (==4.1.3)
Requires-Dist: pandas (==1.0.5)
Requires-Dist: pangres (==2.1)
Requires-Dist: psycopg2-binary (==2.8.5)
Requires-Dist: SQLAlchemy (==1.3.18)
